	
	{
	"ServerName":"ARK France x3 /CrossPlay/Dino+/Nanny/Shop/Mods",
	"ButtonTxt1":"REGLES",
	"ButtonTxt2":"",
	"ButtonTxt3":"",
	"ButtonTxt4":"",
	"ButtonTxt5":"",
	"LinkButtonTxt1":"Wiki",
	"LinkButtonTxt2":"DISCORD",
	"LinkButtonTxt3":"MAPS",
	"LinkButtonTxt4":"DODODEX",
	"LinkButtonTxt5":"",
	"LinkButton1":"https://ark.wiki.gg/fr/wiki/ARK_Wiki",
	"LinkButton2":"https://discord.gg/EUpdPmNFET",
	"Link1Button3":"https://ark-unity.com/ark-survival-ascended/maps/the-island/",
	"Link2Button3":"",
	"Link3Button3":"",
	"Link4Button3":"",
	"Link1Button4":"https://www.dododex.com/",
	"Link2Button4":"",
	"Link3Button4":"",
	"Link4Button4":"",
	"Link1Button5":"",
	"Link2Button5":"",
	"Link3Button5":"",
	"Link4Button5":"",
	"Tab1Panelcount":1,
	"Tab2Panelcount":1,
	"Tab3Panelcount":1,
	"Tab4Panelcount":1,
	"Tab5Panelcount":1,
	"BackgroundTab1":9,
	"BackgroundTab2":0,
	"BackgroundTab3":0,
	"BackgroundTab4":0,
	"BackgroundTab5":0,
	"Background3Color":"",
	"FontColorButtons":"",
	"FontColorServerName":"",
	"FontColorTabTitles":"",
	"FontColorTabText":"",
	"UseSteamBrowserLink1":true,
	"UseSteamBrowserLink2":true,
	"Tab1Title1":"Regles du serveur",
	"Tab1Title2":"",
	"Tab1Title3":"",
	"Tab2Title1":"",
	"Tab2Title2":"",
	"Tab2Title3":"",
	"Tab3Title1":"",
	"Tab3Title2":"",
	"Tab3Title3":"",
	"Tab4Title1":"",
	"Tab4Title2":"",
	"Tab4Title3":"",
	"Tab5Title1":"",
	"Tab5Title2":"",
	"Tab5Title3":"",
	"Tab1Text1":"1=Ceci est un serveur communautaire ce qui signifie jouer en groupe, nous encourageonts donc le fair-play et la bonne ambiance. * 2=Les barrages à castor doivent êtres détruits après votre passage (merci de bien vouloir les vider des items dont vous ne voulez pas) *  3=Ne pas build sur les zones de spawns connus de ressources (Métal,Obsidienne,Ciment,Perles etc...) * 4=Ne pas faire de bases avec des tailles démesurées par rapport à votre besoin * 5=Tout vol doeuf, stuff ainsi que tout acte de pvp sera passible de ban définitif * 6=Interdiction formelle de laisser un Dino en agressif se balader sur la map * 7=Merci de bien vouloir laisser vos structures de récoltes dévérouillées (Extracteur Sève, Pétrole etc) * 8=Ne pas bloquer les ponts et les plages, si votre base bloque un passage merci de bien vouloir laisser vos portes dévérouillées pour laisser les joueurs passer * 9=Il est interdit de bloquer laccès aux grottes ainsi que laccès aux artéfacts * 10=Tout enclos ou piège pour tamer doit être retiré après le taming * 11=Merci de ne pas construire dans les grottes, sur lîle aux herbivores, sur les spots à pingouins, sur les obélisques etc.. * 12=Les drops (Loots Crates) Fonctionnent au premier arrivé, premier servi. Toute tentative de vol dun drop à un joueur sera sanctionnée * 13=Tout manque de respect ou insultes sera immédiatement sanctionné * 14=Nous nous réservons le droit de rajouter des règles dans cette liste sil y a eu oubli de notre part.",
	"Tab1Text2":"",
	"Tab1Text3":"",
	"Tab2Text1":"",
	"Tab2Text2":"",
	"Tab2Text3":"",
	"Tab3Text1":"",
	"Tab3Text2":"",
	"Tab3Text3":"",
	"Tab4Text1":"",
	"Tab4Text2":"",
	"Tab4Text3":"",
	"Tab5Text1":"",
	"Tab5Text2":"",
	"Tab5Text3":""
	}